{
  "September": [
    {
      "date": "September 1",
      "day": "National Chicken Boy Day",
      "body": "Feathers in the breeze, Chicken Boy stands tall and proud, Rooster of the streets."
    },
    {
      "date": "September 2",
      "day": "National Blueberry Popsicle Day",
      "body": "Blueberry delight, Frozen treat on a hot day, Summer's sweetest bite."
    },
    {
      "date": "September 3",
      "day": "National Skyscraper Day",
      "body": "Steel giants so high, Reaching for the endless sky, Urban dreams touch stars."
    },
    {
      "date": "September 4",
      "day": "National Wildlife Day",
      "body": "Creatures roam and play, In nature's grand ballet, Wildlife's wondrous display."
    },
    {
      "date": "September 5",
      "day": "National Cheese Pizza Day",
      "body": "Melted cheese so fine, On a doughy crust divine, Pizza love's design."
    },
    {
      "date": "September 6",
      "day": "National Read a Book Day",
      "body": "Pages come alive, Worlds within the written word, Imagination thrives."
    },
    {
      "date": "September 7",
      "day": "National Salami Day",
      "body": "Cured and savory, Salami's flavor so bold, Charcuterie gold."
    },
    {
      "date": "September 8",
      "day": "National Ampersand Day",
      "body": "Symbol of connection, Binding words with affection, & is perfection."
    },
    {
      "date": "September 9",
      "day": "National Teddy Bear Day",
      "body": "Soft and cuddly friend, Teddy bear, love without end, Comfort they extend."
    },
    {
      "date": "September 10",
      "day": "National Swap Ideas Day",
      "body": "Minds together blend, Ideas shared, new paths to tend, Innovation's trend."
    },
    {
      "date": "September 11",
      "day": "Patriot Day",
      "body": "Flags at half-mast sway, In memory we convey, Heroes of that day."
    },
    {
      "date": "September 12",
      "day": "National Chocolate Milkshake Day",
      "body": "Chocolate swirls in cream, Milkshake, a childhood dream, Sweet delight supreme."
    },
    {
      "date": "September 13",
      "day": "National Grandparents Day",
      "body": "Guidance and embrace, Grandparents' love leaves its trace, Warmth and wisdom's grace."
    },
    {
      "date": "September 14",
      "day": "National Live Creative Day",
      "body": "Colors, forms, and sound, Creativity unbound, Inventive hearts abound."
    },
    {
      "date": "September 15",
      "day": "National Felt Hat Day",
      "body": "Felt hat on the head, Vintage style, old-world thread, Fashion finely bred."
    },
    {
      "date": "September 16",
      "day": "National Guacamole Day",
      "body": "Mashed green and bright, Guacamole's pure delight, Dip into the light."
    },
    {
      "date": "September 17",
      "day": "Constitution Day",
      "body": "Freedom's cornerstone, Constitution's truth is known, Rights we call our own."
    },
    {
      "date": "September 18",
      "day": "National Cheeseburger Day",
      "body": "Juicy patty seared, Cheese and toppings, flavors cheered, Burger love revered."
    },
    {
      "date": "September 19",
      "day": "National Talk Like a Pirate Day",
      "body": "Arr, matey, they say, Pirates speak in their own way, Seafaring display."
    },
    {
      "date": "September 20",
      "day": "National Pepperoni Pizza Day",
      "body": "Pepperoni's zest, Pizza's classic, loved the best, Slices of pure fest."
    },
    {
      "date": "September 21",
      "day": "International Day of Peace",
      "body": "Flags of every hue, Peace for me and peace for you, World's dreams coming true."
    },
    {
      "date": "September 22",
      "day": "National Elephant Appreciation Day",
      "body": "Gentle giants roam, In the wild they find their home, Elephants, we own."
    },
    {
      "date": "September 23",
      "day": "National Great American Pot Pie Day",
      "body": "Flaky crust conceals, Savory fillings, warm appeals, Pot pie's comfort heals."
    },
    {
      "date": "September 24",
      "day": "National Punctuation Day",
      "body": "Periods, commas, dash, Punctuation's rhythmic flash, Grammar's art, a splash."
    },
    {
      "date": "September 25",
      "day": "National Comic Book Day",
      "body": "Ink and paper dance, Heroes rise, villains advance, Comic worlds entrance."
    },
    {
      "date": "September 26",
      "day": "National Pancake Day",
      "body": "Golden, fluffy stacks, Syrup rivers down their backs, Morning joy, no lack."
    },
    {
      "date": "September 27",
      "day": "National Crush a Can Day",
      "body": "Aluminum's clang, Recycle and reduce's the plan, Earth's future in hand."
    },
    {
      "date": "September 28",
      "day": "National Drink Beer Day",
      "body": "Amber liquid gold, Cheers to friends and stories told, Beer's warmth, untold."
    },
    {
      "date": "September 29",
      "day": "National Coffee Day",
      "body": "Brewed to start the day, Coffee's warmth in every way, Caffeine's rich ballet."
    },
    {
      "date": "September 30",
      "day": "National Hot Mulled Cider Day",
      "body": "Spices warm and wide, Cider simmered by fireside, Autumn's sip with pride."
    }
  ]
}